{"ActaEscTip":"D","DepId":"FLORIDA","DepNombre":"Florida","ConvId":3,"ConvNombre":"Colorado - O.D.D.","ConvNomAbre":"Colorado            ","ConvBandera":"Images\\Banderas\\partido_colorado.bmp","ODNConvId":4,"TpoConvId":"INTERNAODD","TotalEnHojas":3668,"TotalALemas":22,"TotalAnulados":14,"TotalBlancoParcial":504,"Total":3704,"Lemas":[{"Id":12,"Nombre":"Partido Colorado       ","Orden":12,"TotalAlLema":22,"Total":3690,"TotalEnHojas":3668,"SubLemas":[{"Id":1323,"Nombre":"BATLLISTAS                                        ","TotalAlSubLema":0,"TotalEnHojas":581,"Total":581,"DepNombre":"Florida","Hojas":[{"Id":960,"Nombre":"200010","Orden":0,"Total":308,"DepNombre":"Florida"},{"Id":961,"Nombre":"200024","Orden":0,"Total":273,"DepNombre":"Florida"}]},{"Id":1324,"Nombre":"CIUDADANOS FLORIDA                                ","TotalAlSubLema":22,"TotalEnHojas":2187,"Total":2209,"DepNombre":"Florida","Hojas":[{"Id":956,"Nombre":"501","Orden":0,"Total":877,"DepNombre":"Florida"},{"Id":957,"Nombre":"603","Orden":0,"Total":497,"DepNombre":"Florida"},{"Id":958,"Nombre":"614","Orden":0,"Total":813,"DepNombre":"Florida"}]},{"Id":1333,"Nombre":"SEGURIDAD Y JUSTICIA                              ","TotalAlSubLema":0,"TotalEnHojas":87,"Total":87,"DepNombre":"Florida","Hojas":[{"Id":959,"Nombre":"11009","Orden":0,"Total":87,"DepNombre":"Florida"}]},{"Id":1334,"Nombre":"FLORIDA BATLLISTA                                 ","TotalAlSubLema":0,"TotalEnHojas":813,"Total":813,"DepNombre":"Florida","Hojas":[{"Id":955,"Nombre":"322","Orden":0,"Total":813,"DepNombre":"Florida"}]}]}]}
