{"ActaEscTip":"P","DepId":"FLORIDA","DepNombre":"Florida","ConvId":6,"ConvNombre":"Nacional - O.D.N.","ConvNomAbre":"Nacional            ","ConvBandera":"Images\\Banderas\\partido_nacional.bmp","ODNConvId":0,"TpoConvId":"INTERNAODN","TotalEnHojas":14098,"TotalALemas":43,"TotalAnulados":38,"TotalBlancoParcial":0,"Total":14179,"Lemas":[{"Id":7,"Nombre":"ANTIA BEHRENS, Enrique Andres","Orden":7,"TotalAlLema":0,"Total":34,"TotalEnHojas":34,"Hojas":[{"Id":2493,"Nombre":"3333","Orden":0,"Total":34,"DepNombre":"Florida"}]},{"Id":9,"Nombre":"IAFIGLIOLA PIMENTEL, Carlos Alberto","Orden":8,"TotalAlLema":0,"Total":74,"TotalEnHojas":74,"Hojas":[{"Id":2495,"Nombre":"252","Orden":0,"Total":74,"DepNombre":"Florida"}]},{"Id":10,"Nombre":"LACALLE POU, Luis Alberto","Orden":9,"TotalAlLema":43,"Total":9933,"TotalEnHojas":9890,"Hojas":[{"Id":2496,"Nombre":"162","Orden":0,"Total":1992,"DepNombre":"Florida"},{"Id":2497,"Nombre":"911","Orden":0,"Total":263,"DepNombre":"Florida"},{"Id":2498,"Nombre":"1262","Orden":0,"Total":647,"DepNombre":"Florida"},{"Id":2499,"Nombre":"6060","Orden":0,"Total":993,"DepNombre":"Florida"},{"Id":2500,"Nombre":"6218","Orden":0,"Total":1365,"DepNombre":"Florida"},{"Id":2501,"Nombre":"6219","Orden":0,"Total":409,"DepNombre":"Florida"},{"Id":2502,"Nombre":"6226","Orden":0,"Total":2263,"DepNombre":"Florida"},{"Id":2503,"Nombre":"6233","Orden":0,"Total":192,"DepNombre":"Florida"},{"Id":2504,"Nombre":"6240","Orden":0,"Total":1766,"DepNombre":"Florida"}]},{"Id":8,"Nombre":"LARRAÑAGA FRAGA, Jorge Washington","Orden":10,"TotalAlLema":0,"Total":788,"TotalEnHojas":788,"Hojas":[{"Id":2494,"Nombre":"250","Orden":0,"Total":788,"DepNombre":"Florida"}]},{"Id":11,"Nombre":"SARTORI PIÑEYRO, Juan José","Orden":11,"TotalAlLema":0,"Total":3312,"TotalEnHojas":3312,"Hojas":[{"Id":2505,"Nombre":"880","Orden":0,"Total":3312,"DepNombre":"Florida"}]}]}
