{"ActaEscTip":"P","DepId":"TACUAREMBO","DepNombre":"Tacuarembó","ConvId":1,"ConvNombre":"Frente Amplio - O.D.D.","ConvNomAbre":"Frente Amplio       ","ConvBandera":"Images\\Banderas\\partido_fa.bmp","ODNConvId":2,"TpoConvId":"INTERNAODD","TotalEnHojas":3988,"TotalALemas":0,"TotalAnulados":16,"TotalBlancoParcial":0,"Total":4004,"Lemas":[{"Id":1,"Nombre":"Frente Amplio                                     ","Orden":1,"TotalAlLema":0,"Total":3988,"TotalEnHojas":3988,"SubLemas":[{"Id":375,"Nombre":"HOJA 5006","TotalAlSubLema":0,"TotalEnHojas":99,"Total":99,"DepNombre":"Tacuarembó","Hojas":[{"Id":1951,"Nombre":"5006","Orden":0,"Total":99,"DepNombre":"Tacuarembó"}]},{"Id":377,"Nombre":"HOJA 777","TotalAlSubLema":0,"TotalEnHojas":241,"Total":241,"DepNombre":"Tacuarembó","Hojas":[{"Id":1944,"Nombre":"777","Orden":0,"Total":241,"DepNombre":"Tacuarembó"}]},{"Id":382,"Nombre":"HOJA 1609","TotalAlSubLema":0,"TotalEnHojas":821,"Total":821,"DepNombre":"Tacuarembó","Hojas":[{"Id":1947,"Nombre":"1609","Orden":0,"Total":821,"DepNombre":"Tacuarembó"}]},{"Id":384,"Nombre":"HOJA 11303","TotalAlSubLema":0,"TotalEnHojas":73,"Total":73,"DepNombre":"Tacuarembó","Hojas":[{"Id":1952,"Nombre":"11303","Orden":0,"Total":73,"DepNombre":"Tacuarembó"}]},{"Id":388,"Nombre":"HOJA 190","TotalAlSubLema":0,"TotalEnHojas":738,"Total":738,"DepNombre":"Tacuarembó","Hojas":[{"Id":1941,"Nombre":"190","Orden":0,"Total":738,"DepNombre":"Tacuarembó"}]},{"Id":392,"Nombre":"HOJA 813","TotalAlSubLema":0,"TotalEnHojas":74,"Total":74,"DepNombre":"Tacuarembó","Hojas":[{"Id":1945,"Nombre":"813","Orden":0,"Total":74,"DepNombre":"Tacuarembó"}]},{"Id":1628,"Nombre":"ARRIBA LOS QUE LUCHAN                             ","TotalAlSubLema":0,"TotalEnHojas":41,"Total":41,"DepNombre":"Tacuarembó","Hojas":[{"Id":1946,"Nombre":"1567","Orden":0,"Total":41,"DepNombre":"Tacuarembó"}]},{"Id":1630,"Nombre":"FRENTE LIBER SEREGNI TACUAREMBO                   ","TotalAlSubLema":0,"TotalEnHojas":309,"Total":309,"DepNombre":"Tacuarembó","Hojas":[{"Id":1950,"Nombre":"2120","Orden":0,"Total":309,"DepNombre":"Tacuarembó"}]},{"Id":1640,"Nombre":"UNIDAD PARA LOS CAMBIOS                           ","TotalAlSubLema":0,"TotalEnHojas":681,"Total":681,"DepNombre":"Tacuarembó","Hojas":[{"Id":1949,"Nombre":"2001","Orden":0,"Total":681,"DepNombre":"Tacuarembó"}]},{"Id":1641,"Nombre":"FRENTE TACUAREMBÓ                                 ","TotalAlSubLema":0,"TotalEnHojas":470,"Total":470,"DepNombre":"Tacuarembó","Hojas":[{"Id":1943,"Nombre":"499","Orden":0,"Total":470,"DepNombre":"Tacuarembó"}]},{"Id":1741,"Nombre":"ALIANZA MAS FRENTE AMPLIO                         ","TotalAlSubLema":0,"TotalEnHojas":27,"Total":27,"DepNombre":"Tacuarembó","Hojas":[{"Id":1948,"Nombre":"1959","Orden":0,"Total":27,"DepNombre":"Tacuarembó"}]},{"Id":1742,"Nombre":"Que el sol brille para todos                      ","TotalAlSubLema":0,"TotalEnHojas":271,"Total":271,"DepNombre":"Tacuarembó","Hojas":[{"Id":1942,"Nombre":"301","Orden":0,"Total":271,"DepNombre":"Tacuarembó"}]},{"Id":1877,"Nombre":"HOJA 11983","TotalAlSubLema":0,"TotalEnHojas":143,"Total":143,"DepNombre":"Tacuarembó","Hojas":[{"Id":1953,"Nombre":"11983","Orden":0,"Total":143,"DepNombre":"Tacuarembó"}]}]}]}
