{"ActaEscTip":"P","DepId":"COLONIA","DepNombre":"Colonia","ConvId":5,"ConvNombre":"Nacional - O.D.D.","ConvNomAbre":"Nacional            ","ConvBandera":"Images\\Banderas\\partido_nacional.bmp","ODNConvId":6,"TpoConvId":"INTERNAODD","TotalEnHojas":21594,"TotalALemas":0,"TotalAnulados":226,"TotalBlancoParcial":0,"Total":21820,"Lemas":[{"Id":6,"Nombre":"Partido Nacional     ","Orden":6,"TotalAlLema":0,"Total":21594,"TotalEnHojas":21594,"SubLemas":[{"Id":1253,"Nombre":"CONCORDIA BLANCA                                  ","TotalAlSubLema":0,"TotalEnHojas":16,"Total":16,"DepNombre":"Colonia","Hojas":[{"Id":777,"Nombre":"3232","Orden":0,"Total":16,"DepNombre":"Colonia"}]},{"Id":1259,"Nombre":"DALE COLONIA                                      ","TotalAlSubLema":0,"TotalEnHojas":1024,"Total":1024,"DepNombre":"Colonia","Hojas":[{"Id":761,"Nombre":"3","Orden":0,"Total":543,"DepNombre":"Colonia"},{"Id":782,"Nombre":"5555","Orden":0,"Total":481,"DepNombre":"Colonia"}]},{"Id":1263,"Nombre":"POR LA VIDA, LA FAMILIA Y LA PATRIA               ","TotalAlSubLema":0,"TotalEnHojas":172,"Total":172,"DepNombre":"Colonia","Hojas":[{"Id":771,"Nombre":"1252","Orden":0,"Total":172,"DepNombre":"Colonia"}]},{"Id":1264,"Nombre":"LA LISTA DE JUAN SARTORI                          ","TotalAlSubLema":0,"TotalEnHojas":1777,"Total":1777,"DepNombre":"Colonia","Hojas":[{"Id":779,"Nombre":"4880","Orden":0,"Total":181,"DepNombre":"Colonia"},{"Id":784,"Nombre":"8008","Orden":0,"Total":287,"DepNombre":"Colonia"},{"Id":785,"Nombre":"8800","Orden":0,"Total":305,"DepNombre":"Colonia"},{"Id":788,"Nombre":"19880","Orden":0,"Total":1004,"DepNombre":"Colonia"}]},{"Id":1265,"Nombre":"NUESTRA PROPUESTA PARA COLONIA                    ","TotalAlSubLema":0,"TotalEnHojas":9556,"Total":9556,"DepNombre":"Colonia","Hojas":[{"Id":765,"Nombre":"222","Orden":0,"Total":79,"DepNombre":"Colonia"},{"Id":778,"Nombre":"3904","Orden":0,"Total":3564,"DepNombre":"Colonia"},{"Id":780,"Nombre":"4904","Orden":0,"Total":462,"DepNombre":"Colonia"},{"Id":781,"Nombre":"5404","Orden":0,"Total":125,"DepNombre":"Colonia"},{"Id":783,"Nombre":"7904","Orden":0,"Total":781,"DepNombre":"Colonia"},{"Id":787,"Nombre":"10904","Orden":0,"Total":52,"DepNombre":"Colonia"},{"Id":789,"Nombre":"20404","Orden":0,"Total":179,"DepNombre":"Colonia"},{"Id":790,"Nombre":"21404","Orden":0,"Total":246,"DepNombre":"Colonia"},{"Id":791,"Nombre":"22404","Orden":0,"Total":225,"DepNombre":"Colonia"},{"Id":792,"Nombre":"23404","Orden":0,"Total":79,"DepNombre":"Colonia"},{"Id":793,"Nombre":"25904","Orden":0,"Total":858,"DepNombre":"Colonia"},{"Id":794,"Nombre":"26404","Orden":0,"Total":227,"DepNombre":"Colonia"},{"Id":795,"Nombre":"27404","Orden":0,"Total":159,"DepNombre":"Colonia"},{"Id":796,"Nombre":"29404","Orden":0,"Total":122,"DepNombre":"Colonia"},{"Id":797,"Nombre":"30404","Orden":0,"Total":41,"DepNombre":"Colonia"},{"Id":798,"Nombre":"32904","Orden":0,"Total":211,"DepNombre":"Colonia"},{"Id":799,"Nombre":"40904","Orden":0,"Total":778,"DepNombre":"Colonia"},{"Id":801,"Nombre":"904904","Orden":0,"Total":1368,"DepNombre":"Colonia"}]},{"Id":1270,"Nombre":"MOVIMIENTO FEDERAL                                ","TotalAlSubLema":0,"TotalEnHojas":6,"Total":6,"DepNombre":"Colonia","Hojas":[{"Id":766,"Nombre":"237","Orden":0,"Total":6,"DepNombre":"Colonia"}]},{"Id":1275,"Nombre":"LA GENTE DEL CAMBIO                               ","TotalAlSubLema":0,"TotalEnHojas":3547,"Total":3547,"DepNombre":"Colonia","Hojas":[{"Id":768,"Nombre":"619","Orden":0,"Total":352,"DepNombre":"Colonia"},{"Id":770,"Nombre":"819","Orden":0,"Total":239,"DepNombre":"Colonia"},{"Id":774,"Nombre":"2519","Orden":0,"Total":323,"DepNombre":"Colonia"},{"Id":775,"Nombre":"2819","Orden":0,"Total":1496,"DepNombre":"Colonia"},{"Id":776,"Nombre":"2880","Orden":0,"Total":876,"DepNombre":"Colonia"},{"Id":800,"Nombre":"56219","Orden":0,"Total":261,"DepNombre":"Colonia"}]},{"Id":1276,"Nombre":"POR LA PATRIA                                     ","TotalAlSubLema":0,"TotalEnHojas":812,"Total":812,"DepNombre":"Colonia","Hojas":[{"Id":773,"Nombre":"1919","Orden":0,"Total":812,"DepNombre":"Colonia"}]},{"Id":1278,"Nombre":"TIEMPOS DE RENOVAR COLONIA                        ","TotalAlSubLema":0,"TotalEnHojas":489,"Total":489,"DepNombre":"Colonia","Hojas":[{"Id":772,"Nombre":"1503","Orden":0,"Total":489,"DepNombre":"Colonia"}]},{"Id":1279,"Nombre":"TODO POR EL PUEBLO                                ","TotalAlSubLema":0,"TotalEnHojas":99,"Total":99,"DepNombre":"Colonia","Hojas":[{"Id":769,"Nombre":"655","Orden":0,"Total":43,"DepNombre":"Colonia"},{"Id":786,"Nombre":"8888","Orden":0,"Total":56,"DepNombre":"Colonia"}]},{"Id":1280,"Nombre":"COLONIA EVOLUCIONA                                ","TotalAlSubLema":0,"TotalEnHojas":3891,"Total":3891,"DepNombre":"Colonia","Hojas":[{"Id":762,"Nombre":"12","Orden":0,"Total":3241,"DepNombre":"Colonia"},{"Id":763,"Nombre":"119","Orden":0,"Total":492,"DepNombre":"Colonia"},{"Id":764,"Nombre":"151","Orden":0,"Total":158,"DepNombre":"Colonia"}]},{"Id":1821,"Nombre":"HOJA 405","TotalAlSubLema":0,"TotalEnHojas":203,"Total":203,"DepNombre":"Colonia","Hojas":[{"Id":767,"Nombre":"405","Orden":0,"Total":203,"DepNombre":"Colonia"}]},{"Id":1822,"Nombre":"HOJA 2","TotalAlSubLema":0,"TotalEnHojas":2,"Total":2,"DepNombre":"Colonia","Hojas":[{"Id":760,"Nombre":"2","Orden":0,"Total":2,"DepNombre":"Colonia"}]}]}]}
