{"ActaEscTip":"D","DepId":"DURAZNO","DepNombre":"Durazno","ConvId":3,"ConvNombre":"Colorado - O.D.D.","ConvNomAbre":"Colorado            ","ConvBandera":"Images\\Banderas\\partido_colorado.bmp","ODNConvId":4,"TpoConvId":"INTERNAODD","TotalEnHojas":3133,"TotalALemas":2,"TotalAnulados":8,"TotalBlancoParcial":432,"Total":3143,"Lemas":[{"Id":12,"Nombre":"Partido Colorado       ","Orden":12,"TotalAlLema":2,"Total":3135,"TotalEnHojas":3133,"SubLemas":[{"Id":1285,"Nombre":"BATLLISTAS DURAZNENSES                            ","TotalAlSubLema":0,"TotalEnHojas":100,"Total":100,"DepNombre":"Durazno","Hojas":[{"Id":863,"Nombre":"1515","Orden":0,"Total":100,"DepNombre":"Durazno"}]},{"Id":1288,"Nombre":"BATLLISTAS DURAZNO                                ","TotalAlSubLema":0,"TotalEnHojas":884,"Total":884,"DepNombre":"Durazno","Hojas":[{"Id":864,"Nombre":"2540","Orden":0,"Total":884,"DepNombre":"Durazno"}]},{"Id":1297,"Nombre":"CIUDADANOS DURAZNO                                ","TotalAlSubLema":2,"TotalEnHojas":1408,"Total":1410,"DepNombre":"Durazno","Hojas":[{"Id":865,"Nombre":"15600","Orden":0,"Total":507,"DepNombre":"Durazno"},{"Id":866,"Nombre":"60022","Orden":0,"Total":901,"DepNombre":"Durazno"}]},{"Id":1872,"Nombre":"URUGUAY BATLLISTA","TotalAlSubLema":0,"TotalEnHojas":121,"Total":121,"DepNombre":"Durazno","Hojas":[{"Id":862,"Nombre":"1015","Orden":0,"Total":121,"DepNombre":"Durazno"}]},{"Id":1873,"Nombre":"HOJA 323","TotalAlSubLema":0,"TotalEnHojas":620,"Total":620,"DepNombre":"Durazno","Hojas":[{"Id":861,"Nombre":"323","Orden":0,"Total":620,"DepNombre":"Durazno"}]}]}]}
