{"ActaEscTip":"P","DepId":"CERROLARGO","DepNombre":"Cerro Largo","ConvId":6,"ConvNombre":"Nacional - O.D.N.","ConvNomAbre":"Nacional            ","ConvBandera":"Images\\Banderas\\partido_nacional.bmp","ODNConvId":0,"TpoConvId":"INTERNAODN","TotalEnHojas":24928,"TotalALemas":176,"TotalAnulados":87,"TotalBlancoParcial":0,"Total":25191,"Lemas":[{"Id":7,"Nombre":"ANTIA BEHRENS, Enrique Andres","Orden":7,"TotalAlLema":12,"Total":14430,"TotalEnHojas":14418,"Hojas":[{"Id":2224,"Nombre":"3","Orden":0,"Total":11375,"DepNombre":"Cerro Largo"},{"Id":2225,"Nombre":"4","Orden":0,"Total":921,"DepNombre":"Cerro Largo"},{"Id":2226,"Nombre":"195","Orden":0,"Total":78,"DepNombre":"Cerro Largo"},{"Id":2227,"Nombre":"319","Orden":0,"Total":235,"DepNombre":"Cerro Largo"},{"Id":2228,"Nombre":"400","Orden":0,"Total":79,"DepNombre":"Cerro Largo"},{"Id":2229,"Nombre":"555","Orden":0,"Total":1730,"DepNombre":"Cerro Largo"}]},{"Id":9,"Nombre":"IAFIGLIOLA PIMENTEL, Carlos Alberto","Orden":8,"TotalAlLema":0,"Total":5,"TotalEnHojas":5,"Hojas":[{"Id":2232,"Nombre":"252","Orden":0,"Total":5,"DepNombre":"Cerro Largo"}]},{"Id":10,"Nombre":"LACALLE POU, Luis Alberto","Orden":9,"TotalAlLema":146,"Total":5426,"TotalEnHojas":5280,"Hojas":[{"Id":2233,"Nombre":"71","Orden":0,"Total":1667,"DepNombre":"Cerro Largo"},{"Id":2234,"Nombre":"403","Orden":0,"Total":1415,"DepNombre":"Cerro Largo"},{"Id":2235,"Nombre":"404","Orden":0,"Total":2112,"DepNombre":"Cerro Largo"},{"Id":2236,"Nombre":"6262","Orden":0,"Total":86,"DepNombre":"Cerro Largo"}]},{"Id":8,"Nombre":"LARRAÑAGA FRAGA, Jorge Washington","Orden":10,"TotalAlLema":1,"Total":1171,"TotalEnHojas":1170,"Hojas":[{"Id":2230,"Nombre":"34","Orden":0,"Total":1019,"DepNombre":"Cerro Largo"},{"Id":2231,"Nombre":"250","Orden":0,"Total":151,"DepNombre":"Cerro Largo"}]},{"Id":11,"Nombre":"SARTORI PIÑEYRO, Juan José","Orden":11,"TotalAlLema":17,"Total":4072,"TotalEnHojas":4055,"Hojas":[{"Id":2237,"Nombre":"58","Orden":0,"Total":1688,"DepNombre":"Cerro Largo"},{"Id":2238,"Nombre":"132","Orden":0,"Total":909,"DepNombre":"Cerro Largo"},{"Id":2239,"Nombre":"880","Orden":0,"Total":948,"DepNombre":"Cerro Largo"},{"Id":2240,"Nombre":"1007","Orden":0,"Total":0,"DepNombre":"Cerro Largo"},{"Id":2241,"Nombre":"8800","Orden":0,"Total":510,"DepNombre":"Cerro Largo"}]}]}
